LICENSE.text
setup.py
init/__init__.py
omarlibone.egg-info/PKG-INFO
omarlibone.egg-info/SOURCES.txt
omarlibone.egg-info/dependency_links.txt
omarlibone.egg-info/top_level.txt