Metadata-Version: 2.1
Name: omarlibone
Version: 1.1
Summary: omar aAAA
Author: omar Style
Classifier: Programming Language :: Python :: 3 
Classifier: Operating System :: OS Independent
Classifier: Natural Language :: English
Classifier: License :: OSI Approved :: MIT License
License-File: LICENSE.text
